fps_helloworld/__init__.py
fps_helloworld/_version.py
fps_helloworld/main.py
fps_helloworld-0.0.3.dist-info/LICENSE
fps_helloworld-0.0.3.dist-info/METADATA
fps_helloworld-0.0.3.dist-info/WHEEL
fps_helloworld-0.0.3.dist-info/entry_points.txt
fps_helloworld-0.0.3.dist-info/top_level.txt
fps_helloworld-0.0.3.dist-info/RECORD
