Metadata-Version: 2.1
Name: fps-helloworld
Version: 0.0.3
Summary: A plugin demo for FPS
Home-page: https://github.com/adriendelsalle/fps
Author: Adrien DELSALLE
Author-email: adrien.delsalle@quantstack.net
License: UNKNOWN
Keywords: server,fastapi,pluggy,plugins
Platform: Windows
Platform: Linux
Platform: Mac OS X
Requires-Python: >=3.7
Requires-Dist: fps
